graphmodex/plotlymodex/__init__.py
graphmodex/plotlymodex/graphs/__init__.py
graphmodex/plotlymodex/graphs/animated_graphs.py
graphmodex/plotlymodex/graphs/frequency.py
graphmodex/plotlymodex/layout/__init__.py
graphmodex/plotlymodex/layout/colors.py
graphmodex/plotlymodex/layout/layout.py
graphmodex/plotlymodex/layout/subplot.py
graphmodex-0.0.5.dist-info/licenses/LICENSE
graphmodex-0.0.5.dist-info/METADATA
graphmodex-0.0.5.dist-info/WHEEL
graphmodex-0.0.5.dist-info/top_level.txt
graphmodex-0.0.5.dist-info/RECORD
