Metadata-Version: 2.4
Name: graphmodex
Version: 0.0.5
Summary: A Python library for graph management
Author-email: Gustavo Meira Filho <gustavojvmf@gmail.com>
License-Expression: MIT
Project-URL: Source, https://github.com/Gumodex/graph-modex
Requires-Python: >=3.8
License-File: LICENSE
Requires-Dist: pandas>=2.0
Requires-Dist: plotly>=6.0
Requires-Dist: nbformat>=4.2.0
Requires-Dist: scipy>=1.10.0
Dynamic: license-file
